<?xml version="1.0" encoding="UTF-8"?>
<beans xmlns="http://www.springframework.org/schema/beans"
       xmlns:xsi="http://www.w3.org/2001/XMLSchema-instance"
       xmlns:aop="http://www.springframework.org/schema/aop"
       xmlns:tx="http://www.springframework.org/schema/tx"
       xsi:schemaLocation="
       http://www.springframework.org/schema/beans http://www.springframework.org/schema/beans/spring-beans-2.5.xsd
       http://www.springframework.org/schema/tx http://www.springframework.org/schema/tx/spring-tx-2.5.xsd
       http://www.springframework.org/schema/aop http://www.springframework.org/schema/aop/spring-aop-2.5.xsd">
  
<bean id="systemrightManager" class="com.yf.system.base.systemright.SystemrightManager">
  	<property name="dataSource">
  	
  		<ref bean="myDataSource" />
  	</property>
  	<property name="sqlMapClient">
  		<ref bean="sqlMapClient" />
  	</property>
  </bean>
  
  
 
  <bean id="systemrightComponentProxy"
  	class="org.springframework.transaction.interceptor.TransactionProxyFactoryBean">
  	<property name="transactionManager">
  		<ref bean="transactionManager" />
  	</property>
  	<property name="target">
	  	 <bean class="com.yf.system.base.systemright.SystemrightComponent">
	        <property name="systemrightManager" ref="systemrightManager"/>
	      </bean>
  	</property>
  	<property name="transactionAttributes">
  		<props>
  			<prop key="create*">PROPAGATION_REQUIRED</prop>
  			<prop key="find*">PROPAGATION_REQUIRED,readOnly</prop>
  			<prop key="excute*">PROPAGATION_REQUIRED</prop>
  			<prop key="update*">PROPAGATION_REQUIRED</prop>
  			<prop key="count*">PROPAGATION_REQUIRED,readOnly</prop>
  		</props>
  	</property>
  </bean>
 <bean id="sysrolerightManager" class="com.yf.system.base.sysroleright.SysrolerightManager">
  	<property name="dataSource">
  		<ref bean="myDataSource" />
  	</property>
  	<property name="sqlMapClient">
  		<ref bean="sqlMapClient" />
  	</property>
  </bean>
  
  
 
  <bean id="sysrolerightComponentProxy"
  	class="org.springframework.transaction.interceptor.TransactionProxyFactoryBean">
  	<property name="transactionManager">
  		<ref bean="transactionManager" />
  	</property>
  	<property name="target">
	  	 <bean class="com.yf.system.base.sysroleright.SysrolerightComponent">
	        <property name="sysrolerightManager" ref="sysrolerightManager"/>
	      </bean>
  	</property>
  	<property name="transactionAttributes">
  		<props>
  			<prop key="create*">PROPAGATION_REQUIRED</prop>
  			<prop key="find*">PROPAGATION_REQUIRED,readOnly</prop>
  			<prop key="excute*">PROPAGATION_REQUIRED</prop>
  			<prop key="update*">PROPAGATION_REQUIRED</prop>
  			<prop key="count*">PROPAGATION_REQUIRED,readOnly</prop>
  		</props>
  	</property>
  </bean>
 
 <bean id="agentrolerefManager" class="com.yf.system.base.agentroleref.AgentrolerefManager">
  	<property name="dataSource">
  		<ref bean="myDataSource" />
  	</property>
  	<property name="sqlMapClient">
  		<ref bean="sqlMapClient" />
  	</property>
  </bean>
  
  
 
  <bean id="agentrolerefComponentProxy"
  	class="org.springframework.transaction.interceptor.TransactionProxyFactoryBean">
  	<property name="transactionManager">
  		<ref bean="transactionManager" />
  	</property>
  	<property name="target">
	  	 <bean class="com.yf.system.base.agentroleref.AgentrolerefComponent">
	        <property name="agentrolerefManager" ref="agentrolerefManager"/>
	      </bean>
  	</property>
  	<property name="transactionAttributes">
  		<props>
  			<prop key="create*">PROPAGATION_REQUIRED</prop>
  			<prop key="find*">PROPAGATION_REQUIRED,readOnly</prop>
  			<prop key="excute*">PROPAGATION_REQUIRED</prop>
  			<prop key="update*">PROPAGATION_REQUIRED</prop>
  			<prop key="count*">PROPAGATION_REQUIRED,readOnly</prop>
  		</props>
  	</property>
  </bean>
 
<bean id="customeragentManager" class="com.yf.system.base.customeragent.CustomeragentManager">
  	<property name="dataSource">
  		<ref bean="myDataSource" />
  	</property>
  	<property name="sqlMapClient">
  		<ref bean="sqlMapClient" />
  	</property>
  </bean>
  
  
 
  <bean id="customeragentComponentProxy"
  	class="org.springframework.transaction.interceptor.TransactionProxyFactoryBean">
  	<property name="transactionManager">
  		<ref bean="transactionManager" />
  	</property>
  	<property name="target">
	  	 <bean class="com.yf.system.base.customeragent.CustomeragentComponent">
	        <property name="customeragentManager" ref="customeragentManager"/>
	      </bean>
  	</property>
  	<property name="transactionAttributes">
  		<props>
  			<prop key="create*">PROPAGATION_REQUIRED</prop>
  			<prop key="find*">PROPAGATION_REQUIRED,readOnly</prop>
  			<prop key="excute*">PROPAGATION_REQUIRED</prop>
  			<prop key="update*">PROPAGATION_REQUIRED</prop>
  			<prop key="count*">PROPAGATION_REQUIRED,readOnly</prop>
  		</props>
  	</property>
  </bean>
 
<bean id="customercreditManager" class="com.yf.system.base.customercredit.CustomercreditManager">
  	<property name="dataSource">
  		<ref bean="myDataSource" />
  	</property>
  	<property name="sqlMapClient">
  		<ref bean="sqlMapClient" />
  	</property>
  </bean>
  
  
 
  <bean id="customercreditComponentProxy"
  	class="org.springframework.transaction.interceptor.TransactionProxyFactoryBean">
  	<property name="transactionManager">
  		<ref bean="transactionManager" />
  	</property>
  	<property name="target">
	  	 <bean class="com.yf.system.base.customercredit.CustomercreditComponent">
	        <property name="customercreditManager" ref="customercreditManager"/>
	      </bean>
  	</property>
  	<property name="transactionAttributes">
  		<props>
  			<prop key="create*">PROPAGATION_REQUIRED</prop>
  			<prop key="find*">PROPAGATION_REQUIRED,readOnly</prop>
  			<prop key="excute*">PROPAGATION_REQUIRED</prop>
  			<prop key="update*">PROPAGATION_REQUIRED</prop>
  			<prop key="count*">PROPAGATION_REQUIRED,readOnly</prop>
  		</props>
  	</property>
  </bean>

  <bean id="customerpassengerManager" class="com.yf.system.base.customerpassenger.CustomerpassengerManager">
  	<property name="dataSource">
  		<ref bean="myDataSource" />
  	</property>
  	<property name="sqlMapClient">
  		<ref bean="sqlMapClient" />
  	</property>
  </bean>
  
  
 
  <bean id="customerpassengerComponentProxy"
  	class="org.springframework.transaction.interceptor.TransactionProxyFactoryBean">
  	<property name="transactionManager">
  		<ref bean="transactionManager" />
  	</property>
  	<property name="target">
	  	 <bean class="com.yf.system.base.customerpassenger.CustomerpassengerComponent">
	        <property name="customerpassengerManager" ref="customerpassengerManager"/>
	      </bean>
  	</property>
  	<property name="transactionAttributes">
  		<props>
  			<prop key="create*">PROPAGATION_REQUIRED</prop>
  			<prop key="find*">PROPAGATION_REQUIRED,readOnly</prop>
  			<prop key="excute*">PROPAGATION_REQUIRED</prop>
  			<prop key="update*">PROPAGATION_REQUIRED</prop>
  			<prop key="count*">PROPAGATION_REQUIRED,readOnly</prop>
  		</props>
  	</property>
  </bean>

  <bean id="customeruserManager" class="com.yf.system.base.customeruser.CustomeruserManager">
  	<property name="dataSource">
  		<ref bean="myDataSource" />
  	</property>
  	<property name="sqlMapClient">
  		<ref bean="sqlMapClient" />
  	</property>
  </bean>
  
  
 
  <bean id="customeruserComponentProxy"
  	class="org.springframework.transaction.interceptor.TransactionProxyFactoryBean">
  	<property name="transactionManager">
  		<ref bean="transactionManager" />
  	</property>
  	<property name="target">
	  	 <bean class="com.yf.system.base.customeruser.CustomeruserComponent">
	        <property name="customeruserManager" ref="customeruserManager"/>
	      </bean>
  	</property>
  	<property name="transactionAttributes">
  		<props>
  			<prop key="create*">PROPAGATION_REQUIRED</prop>
  			<prop key="find*">PROPAGATION_REQUIRED,readOnly</prop>
  			<prop key="excute*">PROPAGATION_REQUIRED</prop>
  			<prop key="update*">PROPAGATION_REQUIRED</prop>
  			<prop key="count*">PROPAGATION_REQUIRED,readOnly</prop>
  		</props>
  	</property>
  </bean>
 <bean id="systemactionManager" class="com.yf.system.base.systemaction.SystemactionManager">
  	<property name="dataSource">
  		<ref bean="myDataSource" />
  	</property>
  	<property name="sqlMapClient">
  		<ref bean="sqlMapClient" />
  	</property>
  </bean>
  
  
 
  <bean id="systemactionComponentProxy"
  	class="org.springframework.transaction.interceptor.TransactionProxyFactoryBean">
  	<property name="transactionManager">
  		<ref bean="transactionManager" />
  	</property>
  	<property name="target">
	  	 <bean class="com.yf.system.base.systemaction.SystemactionComponent">
	        <property name="systemactionManager" ref="systemactionManager"/>
	      </bean>
  	</property>
  	<property name="transactionAttributes">
  		<props>
  			<prop key="create*">PROPAGATION_REQUIRED</prop>
  			<prop key="find*">PROPAGATION_REQUIRED,readOnly</prop>
  			<prop key="excute*">PROPAGATION_REQUIRED</prop>
  			<prop key="update*">PROPAGATION_REQUIRED</prop>
  			<prop key="count*">PROPAGATION_REQUIRED,readOnly</prop>
  		</props>
  	</property>
  </bean>
 <bean id="systemroleManager" class="com.yf.system.base.systemrole.SystemroleManager">
  	<property name="dataSource">
  		<ref bean="myDataSource" />
  	</property>
  	<property name="sqlMapClient">
  		<ref bean="sqlMapClient" />
  	</property>
  </bean>
  
  
 
  <bean id="systemroleComponentProxy"
  	class="org.springframework.transaction.interceptor.TransactionProxyFactoryBean">
  	<property name="transactionManager">
  		<ref bean="transactionManager" />
  	</property>
  	<property name="target">
	  	 <bean class="com.yf.system.base.systemrole.SystemroleComponent">
	        <property name="systemroleManager" ref="systemroleManager"/>
	      </bean>
  	</property>
  	<property name="transactionAttributes">
  		<props>
  			<prop key="create*">PROPAGATION_REQUIRED</prop>
  			<prop key="find*">PROPAGATION_REQUIRED,readOnly</prop>
  			<prop key="excute*">PROPAGATION_REQUIRED</prop>
  			<prop key="update*">PROPAGATION_REQUIRED</prop>
  			<prop key="count*">PROPAGATION_REQUIRED,readOnly</prop>
  		</props>
  	</property>
  </bean>
 
<bean id="telephoneManager" class="com.yf.system.base.telephone.TelephoneManager">
  	<property name="dataSource">
  		<ref bean="myDataSource" />
  	</property>
  	<property name="sqlMapClient">
  		<ref bean="sqlMapClient" />
  	</property>
  </bean>
  
  
 
  <bean id="telephoneComponentProxy"
  	class="org.springframework.transaction.interceptor.TransactionProxyFactoryBean">
  	<property name="transactionManager">
  		<ref bean="transactionManager" />
  	</property>
  	<property name="target">
	  	 <bean class="com.yf.system.base.telephone.TelephoneComponent">
	        <property name="telephoneManager" ref="telephoneManager"/>
	      </bean>
  	</property>
  	<property name="transactionAttributes">
  		<props>
  			<prop key="create*">PROPAGATION_REQUIRED</prop>
  			<prop key="find*">PROPAGATION_REQUIRED,readOnly</prop>
  			<prop key="excute*">PROPAGATION_REQUIRED</prop>
  			<prop key="update*">PROPAGATION_REQUIRED</prop>
  			<prop key="count*">PROPAGATION_REQUIRED,readOnly</prop>
  		</props>
  	</property>
  </bean>
 
  <bean id="sysconfigManager" class="com.yf.system.base.sysconfig.SysconfigManager">
  	<property name="dataSource">
  		<ref bean="myDataSource" />
  	</property>
  	<property name="sqlMapClient">
  		<ref bean="sqlMapClient" />
  	</property>
  </bean>
  
  
 
  <bean id="sysconfigComponentProxy"
  	class="org.springframework.transaction.interceptor.TransactionProxyFactoryBean">
  	<property name="transactionManager">
  		<ref bean="transactionManager" />
  	</property>
  	<property name="target">
	  	 <bean class="com.yf.system.base.sysconfig.SysconfigComponent">
	        <property name="sysconfigManager" ref="sysconfigManager"/>
	      </bean>
  	</property>
  	<property name="transactionAttributes">
  		<props>
  			<prop key="create*">PROPAGATION_REQUIRED</prop>
  			<prop key="find*">PROPAGATION_REQUIRED,readOnly</prop>
  			<prop key="excute*">PROPAGATION_REQUIRED</prop>
  			<prop key="update*">PROPAGATION_REQUIRED</prop>
  			<prop key="count*">PROPAGATION_REQUIRED,readOnly</prop>
  		</props>
  	</property>
  </bean>
 <bean id="infotypeManager" class="com.yf.system.base.infotype.InfotypeManager">
  	<property name="dataSource">
  		<ref bean="myDataSource" />
  	</property>
  	<property name="sqlMapClient">
  		<ref bean="sqlMapClient" />
  	</property>
  </bean>
  
  
 
  <bean id="infotypeComponentProxy"
  	class="org.springframework.transaction.interceptor.TransactionProxyFactoryBean">
  	<property name="transactionManager">
  		<ref bean="transactionManager" />
  	</property>
  	<property name="target">
	  	 <bean class="com.yf.system.base.infotype.InfotypeComponent">
	        <property name="infotypeManager" ref="infotypeManager"/>
	      </bean>
  	</property>
  	<property name="transactionAttributes">
  		<props>
  			<prop key="create*">PROPAGATION_REQUIRED</prop>
  			<prop key="find*">PROPAGATION_REQUIRED,readOnly</prop>
  			<prop key="excute*">PROPAGATION_REQUIRED</prop>
  			<prop key="update*">PROPAGATION_REQUIRED</prop>
  			<prop key="count*">PROPAGATION_REQUIRED,readOnly</prop>
  		</props>
  	</property>
  </bean>
 <bean id="infocontentManager" class="com.yf.system.base.infocontent.InfocontentManager">
  	<property name="dataSource">
  		<ref bean="myDataSource" />
  	</property>
  	<property name="sqlMapClient">
  		<ref bean="sqlMapClient" />
  	</property>
  </bean>
  
  
 
  <bean id="infocontentComponentProxy"
  	class="org.springframework.transaction.interceptor.TransactionProxyFactoryBean">
  	<property name="transactionManager">
  		<ref bean="transactionManager" />
  	</property>
  	<property name="target">
	  	 <bean class="com.yf.system.base.infocontent.InfocontentComponent">
	        <property name="infocontentManager" ref="infocontentManager"/>
	      </bean>
  	</property>
  	<property name="transactionAttributes">
  		<props>
  			<prop key="create*">PROPAGATION_REQUIRED</prop>
  			<prop key="find*">PROPAGATION_REQUIRED,readOnly</prop>
  			<prop key="excute*">PROPAGATION_REQUIRED</prop>
  			<prop key="update*">PROPAGATION_REQUIRED</prop>
  			<prop key="count*">PROPAGATION_REQUIRED,readOnly</prop>
  		</props>
  	</property>
  </bean>
 
 <bean id="exchrecordManager" class="com.yf.system.base.exchrecord.ExchrecordManager">
  	<property name="dataSource">
  		<ref bean="myDataSource" />
  	</property>
  	<property name="sqlMapClient">
  		<ref bean="sqlMapClient" />
  	</property>
  </bean>
  
  
 
  <bean id="exchrecordComponentProxy"
  	class="org.springframework.transaction.interceptor.TransactionProxyFactoryBean">
  	<property name="transactionManager">
  		<ref bean="transactionManager" />
  	</property>
  	<property name="target">
	  	 <bean class="com.yf.system.base.exchrecord.ExchrecordComponent">
	        <property name="exchrecordManager" ref="exchrecordManager"/>
	      </bean>
  	</property>
  	<property name="transactionAttributes">
  		<props>
  			<prop key="create*">PROPAGATION_REQUIRED</prop>
  			<prop key="find*">PROPAGATION_REQUIRED,readOnly</prop>
  			<prop key="excute*">PROPAGATION_REQUIRED</prop>
  			<prop key="update*">PROPAGATION_REQUIRED</prop>
  			<prop key="count*">PROPAGATION_REQUIRED,readOnly</prop>
  		</props>
  	</property>
  </bean>
 
<bean id="prizeinfoManager" class="com.yf.system.base.prizeinfo.PrizeinfoManager">
  	<property name="dataSource">
  		<ref bean="myDataSource" />
  	</property>
  	<property name="sqlMapClient">
  		<ref bean="sqlMapClient" />
  	</property>
  </bean>
  
  
 
  <bean id="prizeinfoComponentProxy"
  	class="org.springframework.transaction.interceptor.TransactionProxyFactoryBean">
  	<property name="transactionManager">
  		<ref bean="transactionManager" />
  	</property>
  	<property name="target">
	  	 <bean class="com.yf.system.base.prizeinfo.PrizeinfoComponent">
	        <property name="prizeinfoManager" ref="prizeinfoManager"/>
	      </bean>
  	</property>
  	<property name="transactionAttributes">
  		<props>
  			<prop key="create*">PROPAGATION_REQUIRED</prop>
  			<prop key="find*">PROPAGATION_REQUIRED,readOnly</prop>
  			<prop key="excute*">PROPAGATION_REQUIRED</prop>
  			<prop key="update*">PROPAGATION_REQUIRED</prop>
  			<prop key="count*">PROPAGATION_REQUIRED,readOnly</prop>
  		</props>
  	</property>
  </bean>
 
  <bean id="prizetypeManager" class="com.yf.system.base.prizetype.PrizetypeManager">
  	<property name="dataSource">
  		<ref bean="myDataSource" />
  	</property>
  	<property name="sqlMapClient">
  		<ref bean="sqlMapClient" />
  	</property>
  </bean>
  
  
 
  <bean id="prizetypeComponentProxy"
  	class="org.springframework.transaction.interceptor.TransactionProxyFactoryBean">
  	<property name="transactionManager">
  		<ref bean="transactionManager" />
  	</property>
  	<property name="target">
	  	 <bean class="com.yf.system.base.prizetype.PrizetypeComponent">
	        <property name="prizetypeManager" ref="prizetypeManager"/>
	      </bean>
  	</property>
  	<property name="transactionAttributes">
  		<props>
  			<prop key="create*">PROPAGATION_REQUIRED</prop>
  			<prop key="find*">PROPAGATION_REQUIRED,readOnly</prop>
  			<prop key="excute*">PROPAGATION_REQUIRED</prop>
  			<prop key="update*">PROPAGATION_REQUIRED</prop>
  			<prop key="count*">PROPAGATION_REQUIRED,readOnly</prop>
  		</props>
  	</property>
  </bean>
 <bean id="traderecordManager" class="com.yf.system.base.traderecord.TraderecordManager">
  	<property name="dataSource">
  		<ref bean="myDataSource" />
  	</property>
  	<property name="sqlMapClient">
  		<ref bean="sqlMapClient" />
  	</property>
  </bean>
  
  
 
  <bean id="traderecordComponentProxy"
  	class="org.springframework.transaction.interceptor.TransactionProxyFactoryBean">
  	<property name="transactionManager">
  		<ref bean="transactionManager" />
  	</property>
  	<property name="target">
	  	 <bean class="com.yf.system.base.traderecord.TraderecordComponent">
	        <property name="traderecordManager" ref="traderecordManager"/>
	      </bean>
  	</property>
  	<property name="transactionAttributes">
  		<props>
  			<prop key="create*">PROPAGATION_REQUIRED</prop>
  			<prop key="find*">PROPAGATION_REQUIRED,readOnly</prop>
  			<prop key="excute*">PROPAGATION_REQUIRED</prop>
  			<prop key="update*">PROPAGATION_REQUIRED</prop>
  			<prop key="count*">PROPAGATION_REQUIRED,readOnly</prop>
  		</props>
  	</property>
  </bean>
  <bean id="ymsendManager" class="com.yf.system.base.ymsend.YmsendManager">
  	<property name="dataSource">
  		<ref bean="myDataSource" />
  	</property>
  	<property name="sqlMapClient">
  		<ref bean="sqlMapClient" />
  	</property>
  </bean>
  
  
 
  <bean id="ymsendComponentProxy"
  	class="org.springframework.transaction.interceptor.TransactionProxyFactoryBean">
  	<property name="transactionManager">
  		<ref bean="transactionManager" />
  	</property>
  	<property name="target">
	  	 <bean class="com.yf.system.base.ymsend.YmsendComponent">
	        <property name="ymsendManager" ref="ymsendManager"/>
	      </bean>
  	</property>
  	<property name="transactionAttributes">
  		<props>
  			<prop key="create*">PROPAGATION_REQUIRED</prop>
  			<prop key="find*">PROPAGATION_REQUIRED,readOnly</prop>
  			<prop key="excute*">PROPAGATION_REQUIRED</prop>
  			<prop key="update*">PROPAGATION_REQUIRED</prop>
  			<prop key="count*">PROPAGATION_REQUIRED,readOnly</prop>
  		</props>
  	</property>
  </bean>
  
   <bean id="ymreceiveManager" class="com.yf.system.base.ymreceive.YmreceiveManager">
  	<property name="dataSource">
  		<ref bean="myDataSource" />
  	</property>
  	<property name="sqlMapClient">
  		<ref bean="sqlMapClient" />
  	</property>
  </bean>
  
  
 
  <bean id="ymreceiveComponentProxy"
  	class="org.springframework.transaction.interceptor.TransactionProxyFactoryBean">
  	<property name="transactionManager">
  		<ref bean="transactionManager" />
  	</property>
  	<property name="target">
	  	 <bean class="com.yf.system.base.ymreceive.YmreceiveComponent">
	        <property name="ymreceiveManager" ref="ymreceiveManager"/>
	      </bean>
  	</property>
  	<property name="transactionAttributes">
  		<props>
  			<prop key="create*">PROPAGATION_REQUIRED</prop>
  			<prop key="find*">PROPAGATION_REQUIRED,readOnly</prop>
  			<prop key="excute*">PROPAGATION_REQUIRED</prop>
  			<prop key="update*">PROPAGATION_REQUIRED</prop>
  			<prop key="count*">PROPAGATION_REQUIRED,readOnly</prop>
  		</props>
  	</property>
  </bean>
  <bean id="departmentManager" class="com.yf.system.base.department.DepartmentManager">
  	<property name="dataSource">
  		<ref bean="myDataSource" />
  	</property>
  	<property name="sqlMapClient">
  		<ref bean="sqlMapClient" />
  	</property>
  </bean>
  
  
 
  <bean id="departmentComponentProxy"
  	class="org.springframework.transaction.interceptor.TransactionProxyFactoryBean">
  	<property name="transactionManager">
  		<ref bean="transactionManager" />
  	</property>
  	<property name="target">
	  	 <bean class="com.yf.system.base.department.DepartmentComponent">
	        <property name="departmentManager" ref="departmentManager"/>
	      </bean>
  	</property>
  	<property name="transactionAttributes">
  		<props>
  			<prop key="create*">PROPAGATION_REQUIRED</prop>
  			<prop key="find*">PROPAGATION_REQUIRED,readOnly</prop>
  			<prop key="excute*">PROPAGATION_REQUIRED</prop>
  			<prop key="update*">PROPAGATION_REQUIRED</prop>
  			<prop key="count*">PROPAGATION_REQUIRED,readOnly</prop>
  		</props>
  	</property>
  </bean>
  
   <bean id="biguserManager" class="com.yf.system.base.biguser.BiguserManager">
  	<property name="dataSource">
  		<ref bean="myDataSource" />
  	</property>
  	<property name="sqlMapClient">
  		<ref bean="sqlMapClient" />
  	</property>
  </bean>
  
  
 
  <bean id="biguserComponentProxy"
  	class="org.springframework.transaction.interceptor.TransactionProxyFactoryBean">
  	<property name="transactionManager">
  		<ref bean="transactionManager" />
  	</property>
  	<property name="target">
	  	 <bean class="com.yf.system.base.biguser.BiguserComponent">
	        <property name="biguserManager" ref="biguserManager"/>
	      </bean>
  	</property>
  	<property name="transactionAttributes">
  		<props>
  			<prop key="create*">PROPAGATION_REQUIRED</prop>
  			<prop key="find*">PROPAGATION_REQUIRED,readOnly</prop>
  			<prop key="excute*">PROPAGATION_REQUIRED</prop>
  			<prop key="update*">PROPAGATION_REQUIRED</prop>
  			<prop key="count*">PROPAGATION_REQUIRED,readOnly</prop>
  		</props>
  	</property>
  </bean>
 
  <bean id="biguserpriceManager" class="com.yf.system.base.biguserprice.BiguserpriceManager">
  	<property name="dataSource">
  		<ref bean="myDataSource" />
  	</property>
  	<property name="sqlMapClient">
  		<ref bean="sqlMapClient" />
  	</property>
  </bean>
  
  
 
  <bean id="biguserpriceComponentProxy"
  	class="org.springframework.transaction.interceptor.TransactionProxyFactoryBean">
  	<property name="transactionManager">
  		<ref bean="transactionManager" />
  	</property>
  	<property name="target">
	  	 <bean class="com.yf.system.base.biguserprice.BiguserpriceComponent">
	        <property name="biguserpriceManager" ref="biguserpriceManager"/>
	      </bean>
  	</property>
  	<property name="transactionAttributes">
  		<props>
  			<prop key="create*">PROPAGATION_REQUIRED</prop>
  			<prop key="find*">PROPAGATION_REQUIRED,readOnly</prop>
  			<prop key="excute*">PROPAGATION_REQUIRED</prop>
  			<prop key="update*">PROPAGATION_REQUIRED</prop>
  			<prop key="count*">PROPAGATION_REQUIRED,readOnly</prop>
  		</props>
  	</property>
  </bean>
  <bean id="repayManager" class="com.yf.system.base.repay.RepayManager">
  	<property name="dataSource">
  		<ref bean="myDataSource" />
  	</property>
  	<property name="sqlMapClient">
  		<ref bean="sqlMapClient" />
  	</property>
  </bean>
  
  
 
  <bean id="repayComponentProxy"
  	class="org.springframework.transaction.interceptor.TransactionProxyFactoryBean">
  	<property name="transactionManager">
  		<ref bean="transactionManager" />
  	</property>
  	<property name="target">
	  	 <bean class="com.yf.system.base.repay.RepayComponent">
	        <property name="repayManager" ref="repayManager"/>
	      </bean>
  	</property>
  	<property name="transactionAttributes">
  		<props>
  			<prop key="create*">PROPAGATION_REQUIRED</prop>
  			<prop key="find*">PROPAGATION_REQUIRED,readOnly</prop>
  			<prop key="excute*">PROPAGATION_REQUIRED</prop>
  			<prop key="update*">PROPAGATION_REQUIRED</prop>
  			<prop key="count*">PROPAGATION_REQUIRED,readOnly</prop>
  		</props>
  	</property>
  </bean>
  <bean id="adcooperateManager" class="com.yf.system.base.adcooperate.AdcooperateManager">
  	<property name="dataSource">
  		<ref bean="myDataSource" />
  	</property>
  	<property name="sqlMapClient">
  		<ref bean="sqlMapClient" />
  	</property>
  </bean>
  
  
 
  <bean id="adcooperateComponentProxy"
  	class="org.springframework.transaction.interceptor.TransactionProxyFactoryBean">
  	<property name="transactionManager">
  		<ref bean="transactionManager" />
  	</property>
  	<property name="target">
	  	 <bean class="com.yf.system.base.adcooperate.AdcooperateComponent">
	        <property name="adcooperateManager" ref="adcooperateManager"/>
	      </bean>
  	</property>
  	<property name="transactionAttributes">
  		<props>
  			<prop key="create*">PROPAGATION_REQUIRED</prop>
  			<prop key="find*">PROPAGATION_REQUIRED,readOnly</prop>
  			<prop key="excute*">PROPAGATION_REQUIRED</prop>
  			<prop key="update*">PROPAGATION_REQUIRED</prop>
  			<prop key="count*">PROPAGATION_REQUIRED,readOnly</prop>
  		</props>
  	</property>
  </bean>
 <bean id="tousuManager" class="com.yf.system.base.tousu.TousuManager">
  	<property name="dataSource">
  		<ref bean="myDataSource" />
  	</property>
  	<property name="sqlMapClient">
  		<ref bean="sqlMapClient" />
  	</property>
  </bean>
  
  
 
  <bean id="tousuComponentProxy"
  	class="org.springframework.transaction.interceptor.TransactionProxyFactoryBean">
  	<property name="transactionManager">
  		<ref bean="transactionManager" />
  	</property>
  	<property name="target">
	  	 <bean class="com.yf.system.base.tousu.TousuComponent">
	        <property name="tousuManager" ref="tousuManager"/>
	      </bean>
  	</property>
  	<property name="transactionAttributes">
  		<props>
  			<prop key="create*">PROPAGATION_REQUIRED</prop>
  			<prop key="find*">PROPAGATION_REQUIRED,readOnly</prop>
  			<prop key="excute*">PROPAGATION_REQUIRED</prop>
  			<prop key="update*">PROPAGATION_REQUIRED</prop>
  			<prop key="count*">PROPAGATION_REQUIRED,readOnly</prop>
  		</props>
  	</property>
  </bean>
  <bean id="wanlixingManager" class="com.yf.system.base.wanlixing.WanlixingManager">
  	<property name="dataSource">
  		<ref bean="myDataSource" />
  	</property>
  	<property name="sqlMapClient">
  		<ref bean="sqlMapClient" />
  	</property>
  </bean>
  
  
 
  <bean id="wanlixingComponentProxy"
  	class="org.springframework.transaction.interceptor.TransactionProxyFactoryBean">
  	<property name="transactionManager">
  		<ref bean="transactionManager" />
  	</property>
  	<property name="target">
	  	 <bean class="com.yf.system.base.wanlixing.WanlixingComponent">
	        <property name="wanlixingManager" ref="wanlixingManager"/>
	      </bean>
  	</property>
  	<property name="transactionAttributes">
  		<props>
  			<prop key="create*">PROPAGATION_REQUIRED</prop>
  			<prop key="find*">PROPAGATION_REQUIRED,readOnly</prop>
  			<prop key="excute*">PROPAGATION_REQUIRED</prop>
  			<prop key="update*">PROPAGATION_REQUIRED</prop>
  			<prop key="count*">PROPAGATION_REQUIRED,readOnly</prop>
  		</props>
  	</property>
  </bean>
 <bean id="qqinfoManager" class="com.yf.system.base.qqinfo.QqinfoManager">
  	<property name="dataSource">
  		<ref bean="myDataSource" />
  	</property>
  	<property name="sqlMapClient">
  		<ref bean="sqlMapClient" />
  	</property>
  </bean>
  
  
 
  <bean id="qqinfoComponentProxy"
  	class="org.springframework.transaction.interceptor.TransactionProxyFactoryBean">
  	<property name="transactionManager">
  		<ref bean="transactionManager" />
  	</property>
  	<property name="target">
	  	 <bean class="com.yf.system.base.qqinfo.QqinfoComponent">
	        <property name="qqinfoManager" ref="qqinfoManager"/>
	      </bean>
  	</property>
  	<property name="transactionAttributes">
  		<props>
  			<prop key="create*">PROPAGATION_REQUIRED</prop>
  			<prop key="find*">PROPAGATION_REQUIRED,readOnly</prop>
  			<prop key="excute*">PROPAGATION_REQUIRED</prop>
  			<prop key="update*">PROPAGATION_REQUIRED</prop>
  			<prop key="count*">PROPAGATION_REQUIRED,readOnly</prop>
  		</props>
  	</property>
  </bean> <bean id="qqtypeManager" class="com.yf.system.base.qqtype.QqtypeManager">
  	<property name="dataSource">
  		<ref bean="myDataSource" />
  	</property>
  	<property name="sqlMapClient">
  		<ref bean="sqlMapClient" />
  	</property>
  </bean>
  
  
 
  <bean id="qqtypeComponentProxy"
  	class="org.springframework.transaction.interceptor.TransactionProxyFactoryBean">
  	<property name="transactionManager">
  		<ref bean="transactionManager" />
  	</property>
  	<property name="target">
	  	 <bean class="com.yf.system.base.qqtype.QqtypeComponent">
	        <property name="qqtypeManager" ref="qqtypeManager"/>
	      </bean>
  	</property>
  	<property name="transactionAttributes">
  		<props>
  			<prop key="create*">PROPAGATION_REQUIRED</prop>
  			<prop key="find*">PROPAGATION_REQUIRED,readOnly</prop>
  			<prop key="excute*">PROPAGATION_REQUIRED</prop>
  			<prop key="update*">PROPAGATION_REQUIRED</prop>
  			<prop key="count*">PROPAGATION_REQUIRED,readOnly</prop>
  		</props>
  	</property>
  </bean>
 <bean id="importmureportManager" class="com.yf.system.base.importmureport.ImportmureportManager">
  	<property name="dataSource">
  		<ref bean="myDataSource" />
  	</property>
  	<property name="sqlMapClient">
  		<ref bean="sqlMapClient" />
  	</property>
  </bean>
  
  
 
  <bean id="importmureportComponentProxy"
  	class="org.springframework.transaction.interceptor.TransactionProxyFactoryBean">
  	<property name="transactionManager">
  		<ref bean="transactionManager" />
  	</property>
  	<property name="target">
	  	 <bean class="com.yf.system.base.importmureport.ImportmureportComponent">
	        <property name="importmureportManager" ref="importmureportManager"/>
	      </bean>
  	</property>
  	<property name="transactionAttributes">
  		<props>
  			<prop key="create*">PROPAGATION_REQUIRED</prop>
  			<prop key="find*">PROPAGATION_REQUIRED,readOnly</prop>
  			<prop key="excute*">PROPAGATION_REQUIRED</prop>
  			<prop key="update*">PROPAGATION_REQUIRED</prop>
  			<prop key="count*">PROPAGATION_REQUIRED,readOnly</prop>
  		</props>
  	</property>
  </bean>
 <bean id="miscellaneousManager" class="com.yf.system.base.miscellaneous.MiscellaneousManager">
  	<property name="dataSource">
  		<ref bean="myDataSource" />
  	</property>
  	<property name="sqlMapClient">
  		<ref bean="sqlMapClient" />
  	</property>
  </bean>
  
  
 
  <bean id="miscellaneousComponentProxy"
  	class="org.springframework.transaction.interceptor.TransactionProxyFactoryBean">
  	<property name="transactionManager">
  		<ref bean="transactionManager" />
  	</property>
  	<property name="target">
	  	 <bean class="com.yf.system.base.miscellaneous.MiscellaneousComponent">
	        <property name="miscellaneousManager" ref="miscellaneousManager"/>
	      </bean>
  	</property>
  	<property name="transactionAttributes">
  		<props>
  			<prop key="create*">PROPAGATION_REQUIRED</prop>
  			<prop key="find*">PROPAGATION_REQUIRED,readOnly</prop>
  			<prop key="excute*">PROPAGATION_REQUIRED</prop>
  			<prop key="update*">PROPAGATION_REQUIRED</prop>
  			<prop key="count*">PROPAGATION_REQUIRED,readOnly</prop>
  		</props>
  	</property>
  </bean>
 <bean id="ticketnumberManager" class="com.yf.system.base.ticketnumber.TicketnumberManager">
  	<property name="dataSource">
  		<ref bean="myDataSource" />
  	</property>
  	<property name="sqlMapClient">
  		<ref bean="sqlMapClient" />
  	</property>
  </bean>
  
  
 
  <bean id="ticketnumberComponentProxy"
  	class="org.springframework.transaction.interceptor.TransactionProxyFactoryBean">
  	<property name="transactionManager">
  		<ref bean="transactionManager" />
  	</property>
  	<property name="target">
	  	 <bean class="com.yf.system.base.ticketnumber.TicketnumberComponent">
	        <property name="ticketnumberManager" ref="ticketnumberManager"/>
	      </bean>
  	</property>
  	<property name="transactionAttributes">
  		<props>
  			<prop key="create*">PROPAGATION_REQUIRED</prop>
  			<prop key="find*">PROPAGATION_REQUIRED,readOnly</prop>
  			<prop key="excute*">PROPAGATION_REQUIRED</prop>
  			<prop key="update*">PROPAGATION_REQUIRED</prop>
  			<prop key="count*">PROPAGATION_REQUIRED,readOnly</prop>
  		</props>
  	</property>
  </bean>
 <bean id="tickettypeManager" class="com.yf.system.base.tickettype.TickettypeManager">
  	<property name="dataSource">
  		<ref bean="myDataSource" />
  	</property>
  	<property name="sqlMapClient">
  		<ref bean="sqlMapClient" />
  	</property>
  </bean>
  
  
 
  <bean id="tickettypeComponentProxy"
  	class="org.springframework.transaction.interceptor.TransactionProxyFactoryBean">
  	<property name="transactionManager">
  		<ref bean="transactionManager" />
  	</property>
  	<property name="target">
	  	 <bean class="com.yf.system.base.tickettype.TickettypeComponent">
	        <property name="tickettypeManager" ref="tickettypeManager"/>
	      </bean>
  	</property>
  	<property name="transactionAttributes">
  		<props>
  			<prop key="create*">PROPAGATION_REQUIRED</prop>
  			<prop key="find*">PROPAGATION_REQUIRED,readOnly</prop>
  			<prop key="excute*">PROPAGATION_REQUIRED</prop>
  			<prop key="update*">PROPAGATION_REQUIRED</prop>
  			<prop key="count*">PROPAGATION_REQUIRED,readOnly</prop>
  		</props>
  	</property>
  </bean>
  <bean id="travelskyreportManager" class="com.yf.system.base.travelskyreport.TravelskyreportManager">
  	<property name="dataSource">
  		<ref bean="myDataSource" />
  	</property>
  	<property name="sqlMapClient">
  		<ref bean="sqlMapClient" />
  	</property>
  </bean>
  
  
 
  <bean id="travelskyreportComponentProxy"
  	class="org.springframework.transaction.interceptor.TransactionProxyFactoryBean">
  	<property name="transactionManager">
  		<ref bean="transactionManager" />
  	</property>
  	<property name="target">
	  	 <bean class="com.yf.system.base.travelskyreport.TravelskyreportComponent">
	        <property name="travelskyreportManager" ref="travelskyreportManager"/>
	      </bean>
  	</property>
  	<property name="transactionAttributes">
  		<props>
  			<prop key="create*">PROPAGATION_REQUIRED</prop>
  			<prop key="find*">PROPAGATION_REQUIRED,readOnly</prop>
  			<prop key="excute*">PROPAGATION_REQUIRED</prop>
  			<prop key="update*">PROPAGATION_REQUIRED</prop>
  			<prop key="count*">PROPAGATION_REQUIRED,readOnly</prop>
  		</props>
  	</property>
  </bean>
  
  <bean id="gerenguazhanfrecManager" class="com.yf.system.base.gerenguazhanfrec.GerenguazhanfrecManager">
  	<property name="dataSource">
  		<ref bean="myDataSource" />
  	</property>
  	<property name="sqlMapClient">
  		<ref bean="sqlMapClient" />
  	</property>
  </bean>
  
  
 
  <bean id="gerenguazhanfrecComponentProxy"
  	class="org.springframework.transaction.interceptor.TransactionProxyFactoryBean">
  	<property name="transactionManager">
  		<ref bean="transactionManager" />
  	</property>
  	<property name="target">
	  	 <bean class="com.yf.system.base.gerenguazhanfrec.GerenguazhanfrecComponent">
	        <property name="gerenguazhanfrecManager" ref="gerenguazhanfrecManager"/>
	      </bean>
  	</property>
  	<property name="transactionAttributes">
  		<props>
  			<prop key="create*">PROPAGATION_REQUIRED</prop>
  			<prop key="find*">PROPAGATION_REQUIRED,readOnly</prop>
  			<prop key="excute*">PROPAGATION_REQUIRED</prop>
  			<prop key="update*">PROPAGATION_REQUIRED</prop>
  			<prop key="count*">PROPAGATION_REQUIRED,readOnly</prop>
  		</props>
  	</property>
  </bean>
  
  
  <bean id="insuranceinfoManager" class="com.yf.system.base.insuranceinfo.InsuranceinfoManager">
  	<property name="dataSource">
  		<ref bean="myDataSource" />
  	</property>
  	<property name="sqlMapClient">
  		<ref bean="sqlMapClient" />
  	</property>
  </bean>
  
  
 
  <bean id="insuranceinfoComponentProxy"
  	class="org.springframework.transaction.interceptor.TransactionProxyFactoryBean">
  	<property name="transactionManager">
  		<ref bean="transactionManager" />
  	</property>
  	<property name="target">
	  	 <bean class="com.yf.system.base.insuranceinfo.InsuranceinfoComponent">
	        <property name="insuranceinfoManager" ref="insuranceinfoManager"/>
	      </bean>
  	</property>
  	<property name="transactionAttributes">
  		<props>
  			<prop key="create*">PROPAGATION_REQUIRED</prop>
  			<prop key="find*">PROPAGATION_REQUIRED,readOnly</prop>
  			<prop key="excute*">PROPAGATION_REQUIRED</prop>
  			<prop key="update*">PROPAGATION_REQUIRED</prop>
  			<prop key="count*">PROPAGATION_REQUIRED,readOnly</prop>
  		</props>
  	</property>
  </bean>
  
  <bean id="qmessageManager" class="com.yf.system.base.qmessage.QmessageManager">
  	<property name="dataSource">
  		<ref bean="myDataSource" />
  	</property>
  	<property name="sqlMapClient">
  		<ref bean="sqlMapClient" />
  	</property>
  </bean>
  
  
 
  <bean id="qmessageComponentProxy"
  	class="org.springframework.transaction.interceptor.TransactionProxyFactoryBean">
  	<property name="transactionManager">
  		<ref bean="transactionManager" />
  	</property>
  	<property name="target">
	  	 <bean class="com.yf.system.base.qmessage.QmessageComponent">
	        <property name="qmessageManager" ref="qmessageManager"/>
	      </bean>
  	</property>
  	<property name="transactionAttributes">
  		<props>
  			<prop key="create*">PROPAGATION_REQUIRED</prop>
  			<prop key="find*">PROPAGATION_REQUIRED,readOnly</prop>
  			<prop key="excute*">PROPAGATION_REQUIRED</prop>
  			<prop key="update*">PROPAGATION_REQUIRED</prop>
  			<prop key="count*">PROPAGATION_REQUIRED,readOnly</prop>
  		</props>
  	</property>
  </bean>
  
  <bean id="creditcardManager" class="com.yf.system.base.creditcard.CreditcardManager">
  	<property name="dataSource">
  		<ref bean="myDataSource" />
  	</property>
  	<property name="sqlMapClient">
  		<ref bean="sqlMapClient" />
  	</property>
  </bean>
  
  
 
  <bean id="creditcardComponentProxy"
  	class="org.springframework.transaction.interceptor.TransactionProxyFactoryBean">
  	<property name="transactionManager">
  		<ref bean="transactionManager" />
  	</property>
  	<property name="target">
	  	 <bean class="com.yf.system.base.creditcard.CreditcardComponent">
	        <property name="creditcardManager" ref="creditcardManager"/>
	      </bean>
  	</property>
  	<property name="transactionAttributes">
  		<props>
  			<prop key="create*">PROPAGATION_REQUIRED</prop>
  			<prop key="find*">PROPAGATION_REQUIRED,readOnly</prop>
  			<prop key="excute*">PROPAGATION_REQUIRED</prop>
  			<prop key="update*">PROPAGATION_REQUIRED</prop>
  			<prop key="count*">PROPAGATION_REQUIRED,readOnly</prop>
  		</props>
  	</property>
  </bean>
  
   <bean id="liudianrecordManager" class="com.yf.system.base.liudianrecord.LiudianrecordManager">
  	<property name="dataSource">
  		<ref bean="myDataSource" />
  	</property>
  	<property name="sqlMapClient">
  		<ref bean="sqlMapClient" />
  	</property>
  </bean>
  
  
 
  <bean id="liudianrecordComponentProxy"
  	class="org.springframework.transaction.interceptor.TransactionProxyFactoryBean">
  	<property name="transactionManager">
  		<ref bean="transactionManager" />
  	</property>
  	<property name="target">
	  	 <bean class="com.yf.system.base.liudianrecord.LiudianrecordComponent">
	        <property name="liudianrecordManager" ref="liudianrecordManager"/>
	      </bean>
  	</property>
  	<property name="transactionAttributes">
  		<props>
  			<prop key="create*">PROPAGATION_REQUIRED</prop>
  			<prop key="find*">PROPAGATION_REQUIRED,readOnly</prop>
  			<prop key="excute*">PROPAGATION_REQUIRED</prop>
  			<prop key="update*">PROPAGATION_REQUIRED</prop>
  			<prop key="count*">PROPAGATION_REQUIRED,readOnly</prop>
  		</props>
  	</property>
  </bean>
  
  <bean id="liudianrefinfoManager" class="com.yf.system.base.liudianrefinfo.LiudianrefinfoManager">
  	<property name="dataSource">
  		<ref bean="myDataSource" />
  	</property>
  	<property name="sqlMapClient">
  		<ref bean="sqlMapClient" />
  	</property>
  </bean>
  
  
 
  <bean id="liudianrefinfoComponentProxy"
  	class="org.springframework.transaction.interceptor.TransactionProxyFactoryBean">
  	<property name="transactionManager">
  		<ref bean="transactionManager" />
  	</property>
  	<property name="target">
	  	 <bean class="com.yf.system.base.liudianrefinfo.LiudianrefinfoComponent">
	        <property name="liudianrefinfoManager" ref="liudianrefinfoManager"/>
	      </bean>
  	</property>
  	<property name="transactionAttributes">
  		<props>
  			<prop key="create*">PROPAGATION_REQUIRED</prop>
  			<prop key="find*">PROPAGATION_REQUIRED,readOnly</prop>
  			<prop key="excute*">PROPAGATION_REQUIRED</prop>
  			<prop key="update*">PROPAGATION_REQUIRED</prop>
  			<prop key="count*">PROPAGATION_REQUIRED,readOnly</prop>
  		</props>
  	</property>
  </bean>
  
  <bean id="settlementtypeManager" class="com.yf.system.base.settlementtype.SettlementtypeManager">
  	<property name="dataSource">
  		<ref bean="myDataSource" />
  	</property>
  	<property name="sqlMapClient">
  		<ref bean="sqlMapClient" />
  	</property>
  </bean>
  
  
 
  <bean id="settlementtypeComponentProxy"
  	class="org.springframework.transaction.interceptor.TransactionProxyFactoryBean">
  	<property name="transactionManager">
  		<ref bean="transactionManager" />
  	</property>
  	<property name="target">
	  	 <bean class="com.yf.system.base.settlementtype.SettlementtypeComponent">
	        <property name="settlementtypeManager" ref="settlementtypeManager"/>
	      </bean>
  	</property>
  	<property name="transactionAttributes">
  		<props>
  			<prop key="create*">PROPAGATION_REQUIRED</prop>
  			<prop key="find*">PROPAGATION_REQUIRED,readOnly</prop>
  			<prop key="excute*">PROPAGATION_REQUIRED</prop>
  			<prop key="update*">PROPAGATION_REQUIRED</prop>
  			<prop key="count*">PROPAGATION_REQUIRED,readOnly</prop>
  		</props>
  	</property>
  </bean>
  
  <bean id="rebateruleManager" class="com.yf.system.base.rebaterule.RebateruleManager">
  	<property name="dataSource">
  		<ref bean="myDataSource" />
  	</property>
  	<property name="sqlMapClient">
  		<ref bean="sqlMapClient" />
  	</property>
  </bean>
  
  
 
  <bean id="rebateruleComponentProxy"
  	class="org.springframework.transaction.interceptor.TransactionProxyFactoryBean">
  	<property name="transactionManager">
  		<ref bean="transactionManager" />
  	</property>
  	<property name="target">
	  	 <bean class="com.yf.system.base.rebaterule.RebateruleComponent">
	        <property name="rebateruleManager" ref="rebateruleManager"/>
	      </bean>
  	</property>
  	<property name="transactionAttributes">
  		<props>
  			<prop key="create*">PROPAGATION_REQUIRED</prop>
  			<prop key="find*">PROPAGATION_REQUIRED,readOnly</prop>
  			<prop key="excute*">PROPAGATION_REQUIRED</prop>
  			<prop key="update*">PROPAGATION_REQUIRED</prop>
  			<prop key="count*">PROPAGATION_REQUIRED,readOnly</prop>
  		</props>
  	</property>
  </bean>
  
  <bean id="vmoneyrecordManager" class="com.yf.system.base.vmoneyrecord.VmoneyrecordManager">
  	<property name="dataSource">
  		<ref bean="myDataSource" />
  	</property>
  	<property name="sqlMapClient">
  		<ref bean="sqlMapClient" />
  	</property>
  </bean>
  
  
 
  <bean id="vmoneyrecordComponentProxy"
  	class="org.springframework.transaction.interceptor.TransactionProxyFactoryBean">
  	<property name="transactionManager">
  		<ref bean="transactionManager" />
  	</property>
  	<property name="target">
	  	 <bean class="com.yf.system.base.vmoneyrecord.VmoneyrecordComponent">
	        <property name="vmoneyrecordManager" ref="vmoneyrecordManager"/>
	      </bean>
  	</property>
  	<property name="transactionAttributes">
  		<props>
  			<prop key="create*">PROPAGATION_REQUIRED</prop>
  			<prop key="find*">PROPAGATION_REQUIRED,readOnly</prop>
  			<prop key="excute*">PROPAGATION_REQUIRED</prop>
  			<prop key="update*">PROPAGATION_REQUIRED</prop>
  			<prop key="count*">PROPAGATION_REQUIRED,readOnly</prop>
  		</props>
  	</property>
  </bean>
  
  
  <bean id="customerintegralrecordManager" class="com.yf.system.base.customerintegralrecord.CustomerintegralrecordManager">
  	<property name="dataSource">
  		<ref bean="myDataSource" />
  	</property>
  	<property name="sqlMapClient">
  		<ref bean="sqlMapClient" />
  	</property>
  </bean>
  
  
 
  <bean id="customerintegralrecordComponentProxy"
  	class="org.springframework.transaction.interceptor.TransactionProxyFactoryBean">
  	<property name="transactionManager">
  		<ref bean="transactionManager" />
  	</property>
  	<property name="target">
	  	 <bean class="com.yf.system.base.customerintegralrecord.CustomerintegralrecordComponent">
	        <property name="customerintegralrecordManager" ref="customerintegralrecordManager"/>
	      </bean>
  	</property>
  	<property name="transactionAttributes">
  		<props>
  			<prop key="create*">PROPAGATION_REQUIRED</prop>
  			<prop key="find*">PROPAGATION_REQUIRED,readOnly</prop>
  			<prop key="excute*">PROPAGATION_REQUIRED</prop>
  			<prop key="update*">PROPAGATION_REQUIRED</prop>
  			<prop key="count*">PROPAGATION_REQUIRED,readOnly</prop>
  		</props>
  	</property>
  </bean>
 
  <bean id="userintegralManager" class="com.yf.system.base.userintegral.UserintegralManager">
  	<property name="dataSource">
  		<ref bean="myDataSource" />
  	</property>
  	<property name="sqlMapClient">
  		<ref bean="sqlMapClient" />
  	</property>
  </bean>
  
  
 
  <bean id="userintegralComponentProxy"
  	class="org.springframework.transaction.interceptor.TransactionProxyFactoryBean">
  	<property name="transactionManager">
  		<ref bean="transactionManager" />
  	</property>
  	<property name="target">
	  	 <bean class="com.yf.system.base.userintegral.UserintegralComponent">
	        <property name="userintegralManager" ref="userintegralManager"/>
	      </bean>
  	</property>
  	<property name="transactionAttributes">
  		<props>
  			<prop key="create*">PROPAGATION_REQUIRED</prop>
  			<prop key="find*">PROPAGATION_REQUIRED,readOnly</prop>
  			<prop key="excute*">PROPAGATION_REQUIRED</prop>
  			<prop key="update*">PROPAGATION_REQUIRED</prop>
  			<prop key="count*">PROPAGATION_REQUIRED,readOnly</prop>
  		</props>
  	</property>
  </bean>
 
 <bean id="integralManager" class="com.yf.system.base.integral.IntegralManager">
  	<property name="dataSource">
  		<ref bean="myDataSource" />
  	</property>
  	<property name="sqlMapClient">
  		<ref bean="sqlMapClient" />
  	</property>
  </bean>
  
  
 
  <bean id="integralComponentProxy"
  	class="org.springframework.transaction.interceptor.TransactionProxyFactoryBean">
  	<property name="transactionManager">
  		<ref bean="transactionManager" />
  	</property>
  	<property name="target">
	  	 <bean class="com.yf.system.base.integral.IntegralComponent">
	        <property name="integralManager" ref="integralManager"/>
	      </bean>
  	</property>
  	<property name="transactionAttributes">
  		<props>
  			<prop key="create*">PROPAGATION_REQUIRED</prop>
  			<prop key="find*">PROPAGATION_REQUIRED,readOnly</prop>
  			<prop key="excute*">PROPAGATION_REQUIRED</prop>
  			<prop key="update*">PROPAGATION_REQUIRED</prop>
  			<prop key="count*">PROPAGATION_REQUIRED,readOnly</prop>
  		</props>
  	</property>
  </bean>
  
   <bean id="rebaterecordManager" class="com.yf.system.base.rebaterecord.RebaterecordManager">
  	<property name="dataSource">
  		<ref bean="myDataSource" />
  	</property>
  	<property name="sqlMapClient">
  		<ref bean="sqlMapClient" />
  	</property>
  </bean>
  
  
 
  <bean id="rebaterecordComponentProxy"
  	class="org.springframework.transaction.interceptor.TransactionProxyFactoryBean">
  	<property name="transactionManager">
  		<ref bean="transactionManager" />
  	</property>
  	<property name="target">
	  	 <bean class="com.yf.system.base.rebaterecord.RebaterecordComponent">
	        <property name="rebaterecordManager" ref="rebaterecordManager"/>
	      </bean>
  	</property>
  	<property name="transactionAttributes">
  		<props>
  			<prop key="create*">PROPAGATION_REQUIRED</prop>
  			<prop key="find*">PROPAGATION_REQUIRED,readOnly</prop>
  			<prop key="excute*">PROPAGATION_REQUIRED</prop>
  			<prop key="update*">PROPAGATION_REQUIRED</prop>
  			<prop key="count*">PROPAGATION_REQUIRED,readOnly</prop>
  		</props>
  	</property>
  </bean>
  
  
  
  <bean id="rechargeManager" class="com.yf.system.base.recharge.RechargeManager">
  	<property name="dataSource">
  		<ref bean="myDataSource" />
  	</property>
  	<property name="sqlMapClient">
  		<ref bean="sqlMapClient" />
  	</property>
  </bean>
  
  
 
  <bean id="rechargeComponentProxy"
  	class="org.springframework.transaction.interceptor.TransactionProxyFactoryBean">
  	<property name="transactionManager">
  		<ref bean="transactionManager" />
  	</property>
  	<property name="target">
	  	 <bean class="com.yf.system.base.recharge.RechargeComponent">
	        <property name="rechargeManager" ref="rechargeManager"/>
	      </bean>
  	</property>
  	<property name="transactionAttributes">
  		<props>
  			<prop key="create*">PROPAGATION_REQUIRED</prop>
  			<prop key="find*">PROPAGATION_REQUIRED,readOnly</prop>
  			<prop key="excute*">PROPAGATION_REQUIRED</prop>
  			<prop key="update*">PROPAGATION_REQUIRED</prop>
  			<prop key="count*">PROPAGATION_REQUIRED,readOnly</prop>
  		</props>
  	</property>
  </bean>
 
 <bean id="qmoneyrechargeManager" class="com.yf.system.base.qmoneyrecharge.QmoneyrechargeManager">
  	<property name="dataSource">
  		<ref bean="myDataSource" />
  	</property>
  	<property name="sqlMapClient">
  		<ref bean="sqlMapClient" />
  	</property>
  </bean>
  
  
 
  <bean id="qmoneyrechargeComponentProxy"
  	class="org.springframework.transaction.interceptor.TransactionProxyFactoryBean">
  	<property name="transactionManager">
  		<ref bean="transactionManager" />
  	</property>
  	<property name="target">
	  	 <bean class="com.yf.system.base.qmoneyrecharge.QmoneyrechargeComponent">
	        <property name="qmoneyrechargeManager" ref="qmoneyrechargeManager"/>
	      </bean>
  	</property>
  	<property name="transactionAttributes">
  		<props>
  			<prop key="create*">PROPAGATION_REQUIRED</prop>
  			<prop key="find*">PROPAGATION_REQUIRED,readOnly</prop>
  			<prop key="excute*">PROPAGATION_REQUIRED</prop>
  			<prop key="update*">PROPAGATION_REQUIRED</prop>
  			<prop key="count*">PROPAGATION_REQUIRED,readOnly</prop>
  		</props>
  	</property>
  </bean>
 
 <!-- 帮助中心开始 -->
 <bean id="helpcenterManager" class="com.yf.system.base.helpcenter.HelpcenterManager">
  	<property name="dataSource">
  		<ref bean="myDataSource" />
  	</property>
  	<property name="sqlMapClient">
  		<ref bean="sqlMapClient" />
  	</property>
  </bean>
  
  
 
  <bean id="helpcenterComponentProxy"
  	class="org.springframework.transaction.interceptor.TransactionProxyFactoryBean">
  	<property name="transactionManager">
  		<ref bean="transactionManager" />
  	</property>
  	<property name="target">
	  	 <bean class="com.yf.system.base.helpcenter.HelpcenterComponent">
	        <property name="helpcenterManager" ref="helpcenterManager"/>
	      </bean>
  	</property>
  	<property name="transactionAttributes">
  		<props>
  			<prop key="create*">PROPAGATION_REQUIRED</prop>
  			<prop key="find*">PROPAGATION_REQUIRED,readOnly</prop>
  			<prop key="excute*">PROPAGATION_REQUIRED</prop>
  			<prop key="update*">PROPAGATION_REQUIRED</prop>
  			<prop key="count*">PROPAGATION_REQUIRED,readOnly</prop>
  		</props>
  	</property>
  </bean>
  
  
  <bean id="helpcenterinfoManager" class="com.yf.system.base.helpcenterinfo.HelpcenterinfoManager">
  	<property name="dataSource">
  		<ref bean="myDataSource" />
  	</property>
  	<property name="sqlMapClient">
  		<ref bean="sqlMapClient" />
  	</property>
  </bean>
  
  
 
  <bean id="helpcenterinfoComponentProxy"
  	class="org.springframework.transaction.interceptor.TransactionProxyFactoryBean">
  	<property name="transactionManager">
  		<ref bean="transactionManager" />
  	</property>
  	<property name="target">
	  	 <bean class="com.yf.system.base.helpcenterinfo.HelpcenterinfoComponent">
	        <property name="helpcenterinfoManager" ref="helpcenterinfoManager"/>
	      </bean>
  	</property>
  	<property name="transactionAttributes">
  		<props>
  			<prop key="create*">PROPAGATION_REQUIRED</prop>
  			<prop key="find*">PROPAGATION_REQUIRED,readOnly</prop>
  			<prop key="excute*">PROPAGATION_REQUIRED</prop>
  			<prop key="update*">PROPAGATION_REQUIRED</prop>
  			<prop key="count*">PROPAGATION_REQUIRED,readOnly</prop>
  		</props>
  	</property>
  </bean>
 
 <bean id="informationManager" class="com.yf.system.base.information.InformationManager">
  	<property name="dataSource">
  		<ref bean="myDataSource" />
  	</property>
  	<property name="sqlMapClient">
  		<ref bean="sqlMapClient" />
  	</property>
  </bean>
  
  
 
  <bean id="informationComponentProxy"
  	class="org.springframework.transaction.interceptor.TransactionProxyFactoryBean">
  	<property name="transactionManager">
  		<ref bean="transactionManager" />
  	</property>
  	<property name="target">
	  	 <bean class="com.yf.system.base.information.InformationComponent">
	        <property name="informationManager" ref="informationManager"/>
	      </bean>
  	</property>
  	<property name="transactionAttributes">
  		<props>
  			<prop key="create*">PROPAGATION_REQUIRED</prop>
  			<prop key="find*">PROPAGATION_REQUIRED,readOnly</prop>
  			<prop key="excute*">PROPAGATION_REQUIRED</prop>
  			<prop key="update*">PROPAGATION_REQUIRED</prop>
  			<prop key="count*">PROPAGATION_REQUIRED,readOnly</prop>
  		</props>
  	</property>
  </bean>
  
  <bean id="informationinfoManager" class="com.yf.system.base.informationinfo.InformationinfoManager">
  	<property name="dataSource">
  		<ref bean="myDataSource" />
  	</property>
  	<property name="sqlMapClient">
  		<ref bean="sqlMapClient" />
  	</property>
  </bean>
  
  
 
  <bean id="informationinfoComponentProxy"
  	class="org.springframework.transaction.interceptor.TransactionProxyFactoryBean">
  	<property name="transactionManager">
  		<ref bean="transactionManager" />
  	</property>
  	<property name="target">
	  	 <bean class="com.yf.system.base.informationinfo.InformationinfoComponent">
	        <property name="informationinfoManager" ref="informationinfoManager"/>
	      </bean>
  	</property>
  	<property name="transactionAttributes">
  		<props>
  			<prop key="create*">PROPAGATION_REQUIRED</prop>
  			<prop key="find*">PROPAGATION_REQUIRED,readOnly</prop>
  			<prop key="excute*">PROPAGATION_REQUIRED</prop>
  			<prop key="update*">PROPAGATION_REQUIRED</prop>
  			<prop key="count*">PROPAGATION_REQUIRED,readOnly</prop>
  		</props>
  	</property>
  </bean>
 <!-- 帮助中心结束 -->
 <!-- 包机开始 -->
 <bean id="planeserviceManager" class="com.yf.system.base.planeservice.PlaneserviceManager">
  	<property name="dataSource">
  		<ref bean="myDataSource" />
  	</property>
  	<property name="sqlMapClient">
  		<ref bean="sqlMapClient" />
  	</property>
  </bean>
  
  
 
  <bean id="planeserviceComponentProxy"
  	class="org.springframework.transaction.interceptor.TransactionProxyFactoryBean">
  	<property name="transactionManager">
  		<ref bean="transactionManager" />
  	</property>
  	<property name="target">
	  	 <bean class="com.yf.system.base.planeservice.PlaneserviceComponent">
	        <property name="planeserviceManager" ref="planeserviceManager"/>
	      </bean>
  	</property>
  	<property name="transactionAttributes">
  		<props>
  			<prop key="create*">PROPAGATION_REQUIRED</prop>
  			<prop key="find*">PROPAGATION_REQUIRED,readOnly</prop>
  			<prop key="excute*">PROPAGATION_REQUIRED</prop>
  			<prop key="update*">PROPAGATION_REQUIRED</prop>
  			<prop key="count*">PROPAGATION_REQUIRED,readOnly</prop>
  		</props>
  	</property>
  </bean>
  <!-- 包机结束 -->
 <!-- dizhi -->
 <bean id="useraddressManager" class="com.yf.system.base.useraddress.UseraddressManager">
  	<property name="dataSource">
  		<ref bean="myDataSource" />
  	</property>
  	<property name="sqlMapClient">
  		<ref bean="sqlMapClient" />
  	</property>
  </bean>
  
  
 
  <bean id="useraddressComponentProxy"
  	class="org.springframework.transaction.interceptor.TransactionProxyFactoryBean">
  	<property name="transactionManager">
  		<ref bean="transactionManager" />
  	</property>
  	<property name="target">
	  	 <bean class="com.yf.system.base.useraddress.UseraddressComponent">
	        <property name="useraddressManager" ref="useraddressManager"/>
	      </bean>
  	</property>
  	<property name="transactionAttributes">
  		<props>
  			<prop key="create*">PROPAGATION_REQUIRED</prop>
  			<prop key="find*">PROPAGATION_REQUIRED,readOnly</prop>
  			<prop key="excute*">PROPAGATION_REQUIRED</prop>
  			<prop key="update*">PROPAGATION_REQUIRED</prop>
  			<prop key="count*">PROPAGATION_REQUIRED,readOnly</prop>
  		</props>
  	</property>
  </bean>
 
 <!--  -->
 
 <!-- 短信组 -->
  <bean id="messgroupManager" class="com.yf.system.base.messgroup.MessgroupManager">
  	<property name="dataSource">
  		<ref bean="myDataSource" />
  	</property>
  	<property name="sqlMapClient">
  		<ref bean="sqlMapClient" />
  	</property>
  </bean>
  
  
 
  <bean id="messgroupComponentProxy"
  	class="org.springframework.transaction.interceptor.TransactionProxyFactoryBean">
  	<property name="transactionManager">
  		<ref bean="transactionManager" />
  	</property>
  	<property name="target">
	  	 <bean class="com.yf.system.base.messgroup.MessgroupComponent">
	        <property name="messgroupManager" ref="messgroupManager"/>
	      </bean>
  	</property>
  	<property name="transactionAttributes">
  		<props>
  			<prop key="create*">PROPAGATION_REQUIRED</prop>
  			<prop key="find*">PROPAGATION_REQUIRED,readOnly</prop>
  			<prop key="excute*">PROPAGATION_REQUIRED</prop>
  			<prop key="update*">PROPAGATION_REQUIRED</prop>
  			<prop key="count*">PROPAGATION_REQUIRED,readOnly</prop>
  		</props>
  	</property>
  </bean>
  <!--  -->
  <!-- 模板 -->
  <bean id="templetManager" class="com.yf.system.base.templet.TempletManager">
  	<property name="dataSource">
  		<ref bean="myDataSource" />
  	</property>
  	<property name="sqlMapClient">
  		<ref bean="sqlMapClient" />
  	</property>
  </bean>
  
  
 
  <bean id="templetComponentProxy"
  	class="org.springframework.transaction.interceptor.TransactionProxyFactoryBean">
  	<property name="transactionManager">
  		<ref bean="transactionManager" />
  	</property>
  	<property name="target">
	  	 <bean class="com.yf.system.base.templet.TempletComponent">
	        <property name="templetManager" ref="templetManager"/>
	      </bean>
  	</property>
  	<property name="transactionAttributes">
  		<props>
  			<prop key="create*">PROPAGATION_REQUIRED</prop>
  			<prop key="find*">PROPAGATION_REQUIRED,readOnly</prop>
  			<prop key="excute*">PROPAGATION_REQUIRED</prop>
  			<prop key="update*">PROPAGATION_REQUIRED</prop>
  			<prop key="count*">PROPAGATION_REQUIRED,readOnly</prop>
  		</props>
  	</property>
  </bean>
  
   <bean id="agentvalueManager" class="com.yf.system.base.agentvalue.AgentvalueManager">
  	<property name="dataSource">
  		<ref bean="myDataSource" />
  	</property>
  	<property name="sqlMapClient">
  		<ref bean="sqlMapClient" />
  	</property>
  </bean>
  
  
 
  <bean id="agentvalueComponentProxy"
  	class="org.springframework.transaction.interceptor.TransactionProxyFactoryBean">
  	<property name="transactionManager">
  		<ref bean="transactionManager" />
  	</property>
  	<property name="target">
	  	 <bean class="com.yf.system.base.agentvalue.AgentvalueComponent">
	        <property name="agentvalueManager" ref="agentvalueManager"/>
	      </bean>
  	</property>
  	<property name="transactionAttributes">
  		<props>
  			<prop key="create*">PROPAGATION_REQUIRED</prop>
  			<prop key="find*">PROPAGATION_REQUIRED,readOnly</prop>
  			<prop key="excute*">PROPAGATION_REQUIRED</prop>
  			<prop key="update*">PROPAGATION_REQUIRED</prop>
  			<prop key="count*">PROPAGATION_REQUIRED,readOnly</prop>
  		</props>
  	</property>
  </bean>
  
  
   <bean id="logindescManager" class="com.yf.system.base.logindesc.LogindescManager">
  	<property name="dataSource">
  		<ref bean="myDataSource" />
  	</property>
  	<property name="sqlMapClient">
  		<ref bean="sqlMapClient" />
  	</property>
  </bean>
  
  
 
  <bean id="logindescComponentProxy"
  	class="org.springframework.transaction.interceptor.TransactionProxyFactoryBean">
  	<property name="transactionManager">
  		<ref bean="transactionManager" />
  	</property>
  	<property name="target">
	  	 <bean class="com.yf.system.base.logindesc.LogindescComponent">
	        <property name="logindescManager" ref="logindescManager"/>
	      </bean>
  	</property>
  	<property name="transactionAttributes">
  		<props>
  			<prop key="create*">PROPAGATION_REQUIRED</prop>
  			<prop key="find*">PROPAGATION_REQUIRED,readOnly</prop>
  			<prop key="excute*">PROPAGATION_REQUIRED</prop>
  			<prop key="update*">PROPAGATION_REQUIRED</prop>
  			<prop key="count*">PROPAGATION_REQUIRED,readOnly</prop>
  		</props>
  	</property>
  </bean>
  
  <bean id="airdelayproveManager" class="com.yf.system.base.airdelayprove.AirdelayproveManager">
  	<property name="dataSource">
  		<ref bean="myDataSource" />
  	</property>
  	<property name="sqlMapClient">
  		<ref bean="sqlMapClient" />
  	</property>
  </bean>
  
  
 
  <bean id="airdelayproveComponentProxy"
  	class="org.springframework.transaction.interceptor.TransactionProxyFactoryBean">
  	<property name="transactionManager">
  		<ref bean="transactionManager" />
  	</property>
  	<property name="target">
	  	 <bean class="com.yf.system.base.airdelayprove.AirdelayproveComponent">
	        <property name="airdelayproveManager" ref="airdelayproveManager"/>
	      </bean>
  	</property>
  	<property name="transactionAttributes">
  		<props>
  			<prop key="create*">PROPAGATION_REQUIRED</prop>
  			<prop key="find*">PROPAGATION_REQUIRED,readOnly</prop>
  			<prop key="excute*">PROPAGATION_REQUIRED</prop>
  			<prop key="update*">PROPAGATION_REQUIRED</prop>
  			<prop key="count*">PROPAGATION_REQUIRED,readOnly</prop>
  		</props>
  	</property>
  </bean>
  
  <bean id="huodonguserManager" class="com.yf.system.base.huodonguser.HuodonguserManager">
  	<property name="dataSource">
  		<ref bean="myDataSource" />
  	</property>
  	<property name="sqlMapClient">
  		<ref bean="sqlMapClient" />
  	</property>
  </bean>
  
  
 
  <bean id="huodonguserComponentProxy"
  	class="org.springframework.transaction.interceptor.TransactionProxyFactoryBean">
  	<property name="transactionManager">
  		<ref bean="transactionManager" />
  	</property>
  	<property name="target">
	  	 <bean class="com.yf.system.base.huodonguser.HuodonguserComponent">
	        <property name="huodonguserManager" ref="huodonguserManager"/>
	      </bean>
  	</property>
  	<property name="transactionAttributes">
  		<props>
  			<prop key="create*">PROPAGATION_REQUIRED</prop>
  			<prop key="find*">PROPAGATION_REQUIRED,readOnly</prop>
  			<prop key="excute*">PROPAGATION_REQUIRED</prop>
  			<prop key="update*">PROPAGATION_REQUIRED</prop>
  			<prop key="count*">PROPAGATION_REQUIRED,readOnly</prop>
  		</props>
  	</property>
  </bean>
  <bean id="qqinfonewManager" class="com.yf.system.base.qqinfonew.QqinfonewManager">
  	<property name="dataSource">
  		<ref bean="myDataSource" />
  	</property>
  	<property name="sqlMapClient">
  		<ref bean="sqlMapClient" />
  	</property>
  </bean>
  
  
 
  <bean id="qqinfonewComponentProxy"
  	class="org.springframework.transaction.interceptor.TransactionProxyFactoryBean">
  	<property name="transactionManager">
  		<ref bean="transactionManager" />
  	</property>
  	<property name="target">
	  	 <bean class="com.yf.system.base.qqinfonew.QqinfonewComponent">
	        <property name="qqinfonewManager" ref="qqinfonewManager"/>
	      </bean>
  	</property>
  	<property name="transactionAttributes">
  		<props>
  			<prop key="create*">PROPAGATION_REQUIRED</prop>
  			<prop key="find*">PROPAGATION_REQUIRED,readOnly</prop>
  			<prop key="excute*">PROPAGATION_REQUIRED</prop>
  			<prop key="update*">PROPAGATION_REQUIRED</prop>
  			<prop key="count*">PROPAGATION_REQUIRED,readOnly</prop>
  		</props>
  	</property>
  </bean>
  <bean id="qqtypenewManager" class="com.yf.system.base.qqtypenew.QqtypenewManager">
  	<property name="dataSource">
  		<ref bean="myDataSource" />
  	</property>
  	<property name="sqlMapClient">
  		<ref bean="sqlMapClient" />
  	</property>
  </bean>
  
  
 
  <bean id="qqtypenewComponentProxy"
  	class="org.springframework.transaction.interceptor.TransactionProxyFactoryBean">
  	<property name="transactionManager">
  		<ref bean="transactionManager" />
  	</property>
  	<property name="target">
	  	 <bean class="com.yf.system.base.qqtypenew.QqtypenewComponent">
	        <property name="qqtypenewManager" ref="qqtypenewManager"/>
	      </bean>
  	</property>
  	<property name="transactionAttributes">
  		<props>
  			<prop key="create*">PROPAGATION_REQUIRED</prop>
  			<prop key="find*">PROPAGATION_REQUIRED,readOnly</prop>
  			<prop key="excute*">PROPAGATION_REQUIRED</prop>
  			<prop key="update*">PROPAGATION_REQUIRED</prop>
  			<prop key="count*">PROPAGATION_REQUIRED,readOnly</prop>
  		</props>
  	</property>
  </bean>
  
  <bean id="txorderManager" class="com.yf.system.base.txorder.TxorderManager">
  	<property name="dataSource">
  		<ref bean="myDataSource" />
  	</property>
  	<property name="sqlMapClient">
  		<ref bean="sqlMapClient" />
  	</property>
  </bean>
  
  
 
  <bean id="txorderComponentProxy"
  	class="org.springframework.transaction.interceptor.TransactionProxyFactoryBean">
  	<property name="transactionManager">
  		<ref bean="transactionManager" />
  	</property>
  	<property name="target">
	  	 <bean class="com.yf.system.base.txorder.TxorderComponent">
	        <property name="txorderManager" ref="txorderManager"/>
	      </bean>
  	</property>
  	<property name="transactionAttributes">
  		<props>
  			<prop key="create*">PROPAGATION_REQUIRED</prop>
  			<prop key="find*">PROPAGATION_REQUIRED,readOnly</prop>
  			<prop key="excute*">PROPAGATION_REQUIRED</prop>
  			<prop key="update*">PROPAGATION_REQUIRED</prop>
  			<prop key="count*">PROPAGATION_REQUIRED,readOnly</prop>
  		</props>
  	</property>
  </bean>
  
  <bean id="txuserinfoManager" class="com.yf.system.base.txuserinfo.TxuserinfoManager">
  	<property name="dataSource">
  		<ref bean="myDataSource" />
  	</property>
  	<property name="sqlMapClient">
  		<ref bean="sqlMapClient" />
  	</property>
  </bean>
  
  
 
  <bean id="txuserinfoComponentProxy"
  	class="org.springframework.transaction.interceptor.TransactionProxyFactoryBean">
  	<property name="transactionManager">
  		<ref bean="transactionManager" />
  	</property>
  	<property name="target">
	  	 <bean class="com.yf.system.base.txuserinfo.TxuserinfoComponent">
	        <property name="txuserinfoManager" ref="txuserinfoManager"/>
	      </bean>
  	</property>
  	<property name="transactionAttributes">
  		<props>
  			<prop key="create*">PROPAGATION_REQUIRED</prop>
  			<prop key="find*">PROPAGATION_REQUIRED,readOnly</prop>
  			<prop key="excute*">PROPAGATION_REQUIRED</prop>
  			<prop key="update*">PROPAGATION_REQUIRED</prop>
  			<prop key="count*">PROPAGATION_REQUIRED,readOnly</prop>
  		</props>
  	</property>
  </bean>
  
  <bean id="withbankManager" class="com.yf.system.base.withbank.WithbankManager">
  	<property name="dataSource">
  		<ref bean="myDataSource" />
  	</property>
  	<property name="sqlMapClient">
  		<ref bean="sqlMapClient" />
  	</property>
  </bean>
  
  
 
  <bean id="withbankComponentProxy"
  	class="org.springframework.transaction.interceptor.TransactionProxyFactoryBean">
  	<property name="transactionManager">
  		<ref bean="transactionManager" />
  	</property>
  	<property name="target">
	  	 <bean class="com.yf.system.base.withbank.WithbankComponent">
	        <property name="withbankManager" ref="withbankManager"/>
	      </bean>
  	</property>
  	<property name="transactionAttributes">
  		<props>
  			<prop key="create*">PROPAGATION_REQUIRED</prop>
  			<prop key="find*">PROPAGATION_REQUIRED,readOnly</prop>
  			<prop key="excute*">PROPAGATION_REQUIRED</prop>
  			<prop key="update*">PROPAGATION_REQUIRED</prop>
  			<prop key="count*">PROPAGATION_REQUIRED,readOnly</prop>
  		</props>
  	</property>
  </bean>
  
  
   <bean id="ymuserManager" class="com.yf.system.base.ymuser.YmuserManager">
  	<property name="dataSource">
  		<ref bean="myDataSource" />
  	</property>
  	<property name="sqlMapClient">
  		<ref bean="sqlMapClient" />
  	</property>
  </bean>
  
  
 
  <bean id="ymuserComponentProxy"
  	class="org.springframework.transaction.interceptor.TransactionProxyFactoryBean">
  	<property name="transactionManager">
  		<ref bean="transactionManager" />
  	</property>
  	<property name="target">
	  	 <bean class="com.yf.system.base.ymuser.YmuserComponent">
	        <property name="ymuserManager" ref="ymuserManager"/>
	      </bean>
  	</property>
  	<property name="transactionAttributes">
  		<props>
  			<prop key="create*">PROPAGATION_REQUIRED</prop>
  			<prop key="find*">PROPAGATION_REQUIRED,readOnly</prop>
  			<prop key="excute*">PROPAGATION_REQUIRED</prop>
  			<prop key="update*">PROPAGATION_REQUIRED</prop>
  			<prop key="count*">PROPAGATION_REQUIRED,readOnly</prop>
  		</props>
  	</property>
  </bean>
  <bean id="ympayManager" class="com.yf.system.base.ympay.YmpayManager">
  	<property name="dataSource">
  		<ref bean="myDataSource" />
  	</property>
  	<property name="sqlMapClient">
  		<ref bean="sqlMapClient" />
  	</property>
  </bean>
  
  
 
  <bean id="ympayComponentProxy"
  	class="org.springframework.transaction.interceptor.TransactionProxyFactoryBean">
  	<property name="transactionManager">
  		<ref bean="transactionManager" />
  	</property>
  	<property name="target">
	  	 <bean class="com.yf.system.base.ympay.YmpayComponent">
	        <property name="ympayManager" ref="ympayManager"/>
	      </bean>
  	</property>
  	<property name="transactionAttributes">
  		<props>
  			<prop key="create*">PROPAGATION_REQUIRED</prop>
  			<prop key="find*">PROPAGATION_REQUIRED,readOnly</prop>
  			<prop key="excute*">PROPAGATION_REQUIRED</prop>
  			<prop key="update*">PROPAGATION_REQUIRED</prop>
  			<prop key="count*">PROPAGATION_REQUIRED,readOnly</prop>
  		</props>
  	</property>
  </bean>
  <!--  -->
 <bean id="menberService" class="com.yf.system.base.service.MemberService" scope="singleton">
    <property name="cache" value="true"/>
    <property name="qqinfoComponent" ref="qqinfoComponentProxy"/>	
    <property name="qqtypeComponent" ref="qqtypeComponentProxy"/>
    <property name="importmureportComponent" ref="importmureportComponentProxy"/>
    <property name="miscellaneousComponent" ref="miscellaneousComponentProxy"/>		
    <property name="ticketnumberComponent" ref="ticketnumberComponentProxy"/>
    <property name="tickettypeComponent" ref="tickettypeComponentProxy"/>
    <property name="travelskyreportComponent" ref="travelskyreportComponentProxy"/>			
    <property name="systemrightComponent" ref="systemrightComponentProxy"/>	
    <property name="sysrolerightComponent" ref="sysrolerightComponentProxy"/>	
    <property name="agentrolerefComponent" ref="agentrolerefComponentProxy"/>	
    <property name="customeragentComponent" ref="customeragentComponentProxy"/>	
    <property name="customercreditComponent" ref="customercreditComponentProxy"/>	
    <property name="customerpassengerComponent" ref="customerpassengerComponentProxy"/>
    <property name="customeruserComponent" ref="customeruserComponentProxy"/>
    <property name="systemactionComponent" ref="systemactionComponentProxy"/>	
    <property name="systemroleComponent" ref="systemroleComponentProxy"/>
    <property name="telephoneComponent" ref="telephoneComponentProxy"/>		
    <property name="sysconfigComponent" ref="sysconfigComponentProxy"/>	
    <property name="infotypeComponent" ref="infotypeComponentProxy"/>
    <property name="infocontentComponent" ref="infocontentComponentProxy"/>	
    <property name="exchrecordComponent" ref="exchrecordComponentProxy"/>
    <property name="prizeinfoComponent" ref="prizeinfoComponentProxy"/>		
    <property name="prizetypeComponent" ref="prizetypeComponentProxy"/>	
    <property name="traderecordComponent" ref="traderecordComponentProxy"/>	
    <property name="ymsendComponent" ref="ymsendComponentProxy"/>	
    <property name="ymreceiveComponent" ref="ymreceiveComponentProxy"/>	
    <property name="departmentComponent" ref="departmentComponentProxy"/>	
    <property name="biguserComponent" ref="biguserComponentProxy"/>	
   	<property name="biguserpriceComponent" ref="biguserpriceComponentProxy"/>	
   	<property name="repayComponent" ref="repayComponentProxy"/>		
   	<property name="adcooperateComponent" ref="adcooperateComponentProxy"/>
   	<property name="tousuComponent" ref="tousuComponentProxy"/>	
   	<property name="wanlixingComponent" ref="wanlixingComponentProxy"/>		
   	<property name="gerenguazhanfrecComponent" ref="gerenguazhanfrecComponentProxy"/>
   	<property name="insuranceinfoComponent" ref="insuranceinfoComponentProxy"/>	
   	<property name="qmessageComponent" ref="qmessageComponentProxy"/>
   	<property name="creditcardComponent" ref="creditcardComponentProxy"/>
   	<property name="liudianrecordComponent" ref="liudianrecordComponentProxy"/>	
   	<property name="liudianrefinfoComponent" ref="liudianrefinfoComponentProxy"/>
   	<property name="settlementtypeComponent" ref="settlementtypeComponentProxy"/>
   	<property name="rebateruleComponent" ref="rebateruleComponentProxy"/>	
   	<property name="userintegralComponent" ref="userintegralComponentProxy"/>						
   	<property name="vmoneyrecordComponent" ref="vmoneyrecordComponentProxy"/>	
   	<property name="customerintegralrecordComponent" ref="customerintegralrecordComponentProxy"/>
   	<property name="integralComponent" ref="integralComponentProxy"/>
   	<property name="rebaterecordComponent" ref="rebaterecordComponentProxy"/>
    <property name="rechargeComponent" ref="rechargeComponentProxy"/>
    <property name="qmoneyrechargeComponent" ref="qmoneyrechargeComponentProxy"/>
    <!-- 帮助中心开始 -->	
    <property name="helpcenterComponent" ref="helpcenterComponentProxy"/>
    <property name="helpcenterinfoComponent" ref="helpcenterinfoComponentProxy"/>
    <property name="informationComponent" ref="informationComponentProxy"/>		
    <property name="informationinfoComponent" ref="informationinfoComponentProxy"/>		
    <!-- 帮助中心结束 -->		
    <!-- 包机开始 -->
    <property name="planeserviceComponent" ref="planeserviceComponentProxy"/>	
    <!-- 包机结束 -->	
    <!-- dizhi -->		
    <property name="useraddressComponent" ref="useraddressComponentProxy"/>		
    <!--  -->
    
    <property name="messgroupComponent" ref="messgroupComponentProxy"/>	
    
    <property name="templetComponent" ref="templetComponentProxy"/>
    
    <property name="agentvalueComponent" ref="agentvalueComponentProxy"/>	
    
    <property name="logindescComponent" ref="logindescComponentProxy"/>	
    
    <property name="airdelayproveComponent" ref="airdelayproveComponentProxy"/>	
    
    <property name="huodonguserComponent" ref="huodonguserComponentProxy"/>
    
    <property name="qqinfonewComponent" ref="qqinfonewComponentProxy"/>
    
    <property name="qqtypenewComponent" ref="qqtypenewComponentProxy"/>		
    
    <property name="txorderComponent" ref="txorderComponentProxy"/>
    
    <property name="txuserinfoComponent" ref="txuserinfoComponentProxy"/>
    
    <!-- 提现 -->
    <property name="withbankComponent" ref="withbankComponentProxy"/>	
    
    <property name="ymuserComponent" ref="ymuserComponentProxy"/>	
    	
    <property name="ympayComponent" ref="ympayComponentProxy"/>	
    
   </bean>
	
<bean name="/IMemberService"
	class="org.springframework.remoting.caucho.HessianServiceExporter">
	<property name="service" ref="menberService" />
	<property name="serviceInterface"
		value="com.yf.system.base.service.IMemberService" />
</bean>

</beans>

 
 
